graphql_to_postman/__about__.py
graphql_to_postman/__init__.py
graphql_to_postman/generate_collection.py
graphql_to_postman/main.py
graphql_to_postman/helpers/helper.py
graphql_to_postman/templates/introspection-query.txt
graphql_to_postman-0.1.0.dist-info/METADATA
graphql_to_postman-0.1.0.dist-info/WHEEL
graphql_to_postman-0.1.0.dist-info/entry_points.txt
graphql_to_postman-0.1.0.dist-info/licenses/LICENSE.txt
graphql_to_postman-0.1.0.dist-info/RECORD
