Metadata-Version: 2.4
Name: graphql-to-postman
Version: 0.1.0
Summary: A Python package which converts a given graphql URL to a postman collection
Project-URL: Documentation, https://github.com/DeepakSan/graphql-to-postman/blob/main/README.md
Project-URL: Issues, https://github.com/DeepakSan/graphql-to-postman/issues
Project-URL: Source, https://github.com/DeepakSan/graphql-to-postman
Author-email: Deepak Sanjay S J <deepaksanjaysj@gmail.com>
Maintainer-email: Deepak Sanjay S J <deepaksanjaysj@gmail.com>
License-Expression: MIT
License-File: LICENSE.txt
Keywords: graphql,graphql_to_postman,postman
Classifier: Development Status :: 4 - Beta
Classifier: Framework :: Hatch
Classifier: License :: OSI Approved :: MIT License
Classifier: Programming Language :: Python
Classifier: Programming Language :: Python :: 3.12
Classifier: Topic :: Software Development :: Libraries :: Python Modules
Requires-Python: >=3.8
Requires-Dist: argparse
Requires-Dist: requests
